{
    "name": "pipeline1",
    "properties": {
        "activities": [
            {
                "name": "agency_flow",
                "type": "ExecuteDataFlow",
                "dependsOn": [],
                "policy": {
                    "timeout": "0.12:00:00",
                    "retry": 0,
                    "retryIntervalInSeconds": 30,
                    "secureOutput": false,
                    "secureInput": false
                },
                "userProperties": [],
                "typeProperties": {
                    "dataflow": {
                        "referenceName": "agency_flow",
                        "type": "DataFlowReference"
                    },
                    "compute": {
                        "coreCount": 8,
                        "computeType": "General"
                    },
                    "traceLevel": "Fine"
                }
            },
            {
                "name": "emp_flow",
                "type": "ExecuteDataFlow",
                "dependsOn": [],
                "policy": {
                    "timeout": "0.12:00:00",
                    "retry": 0,
                    "retryIntervalInSeconds": 30,
                    "secureOutput": false,
                    "secureInput": false
                },
                "userProperties": [],
                "typeProperties": {
                    "dataflow": {
                        "referenceName": "emp_flow",
                        "type": "DataFlowReference"
                    },
                    "compute": {
                        "coreCount": 8,
                        "computeType": "General"
                    },
                    "traceLevel": "Fine"
                }
            },
            {
                "name": "title_flow",
                "type": "ExecuteDataFlow",
                "dependsOn": [],
                "policy": {
                    "timeout": "0.12:00:00",
                    "retry": 0,
                    "retryIntervalInSeconds": 30,
                    "secureOutput": false,
                    "secureInput": false
                },
                "userProperties": [],
                "typeProperties": {
                    "dataflow": {
                        "referenceName": "title_flow",
                        "type": "DataFlowReference"
                    },
                    "compute": {
                        "coreCount": 8,
                        "computeType": "General"
                    },
                    "traceLevel": "Fine"
                }
            },
            {
                "name": "NYC_Payroll_2020_flow",
                "type": "ExecuteDataFlow",
                "dependsOn": [
                    {
                        "activity": "agency_flow",
                        "dependencyConditions": [
                            "Completed"
                        ]
                    },
                    {
                        "activity": "emp_flow",
                        "dependencyConditions": [
                            "Completed"
                        ]
                    },
                    {
                        "activity": "title_flow",
                        "dependencyConditions": [
                            "Completed"
                        ]
                    }
                ],
                "policy": {
                    "timeout": "0.12:00:00",
                    "retry": 0,
                    "retryIntervalInSeconds": 30,
                    "secureOutput": false,
                    "secureInput": false
                },
                "userProperties": [],
                "typeProperties": {
                    "dataflow": {
                        "referenceName": "NYC_Payroll_2020_flow",
                        "type": "DataFlowReference"
                    },
                    "compute": {
                        "coreCount": 8,
                        "computeType": "General"
                    },
                    "traceLevel": "Fine"
                }
            },
            {
                "name": "NYC_Payroll_2021_flow",
                "type": "ExecuteDataFlow",
                "dependsOn": [
                    {
                        "activity": "agency_flow",
                        "dependencyConditions": [
                            "Completed"
                        ]
                    },
                    {
                        "activity": "emp_flow",
                        "dependencyConditions": [
                            "Completed"
                        ]
                    },
                    {
                        "activity": "title_flow",
                        "dependencyConditions": [
                            "Completed"
                        ]
                    }
                ],
                "policy": {
                    "timeout": "0.12:00:00",
                    "retry": 0,
                    "retryIntervalInSeconds": 30,
                    "secureOutput": false,
                    "secureInput": false
                },
                "userProperties": [],
                "typeProperties": {
                    "dataflow": {
                        "referenceName": "NYC_Payroll_2021_flow",
                        "type": "DataFlowReference"
                    },
                    "compute": {
                        "coreCount": 8,
                        "computeType": "General"
                    },
                    "traceLevel": "Fine"
                }
            },
            {
                "name": "NYC_Payroll_Summary_flow",
                "type": "ExecuteDataFlow",
                "dependsOn": [
                    {
                        "activity": "NYC_Payroll_2020_flow",
                        "dependencyConditions": [
                            "Completed"
                        ]
                    },
                    {
                        "activity": "NYC_Payroll_2021_flow",
                        "dependencyConditions": [
                            "Completed"
                        ]
                    }
                ],
                "policy": {
                    "timeout": "0.12:00:00",
                    "retry": 0,
                    "retryIntervalInSeconds": 30,
                    "secureOutput": false,
                    "secureInput": false
                },
                "userProperties": [],
                "typeProperties": {
                    "dataflow": {
                        "referenceName": "NYC_Payroll_Summary_flow",
                        "type": "DataFlowReference",
                        "parameters": {
                            "dataflow_param_fiscalyear": 2020
                        }
                    },
                    "compute": {
                        "coreCount": 8,
                        "computeType": "General"
                    },
                    "traceLevel": "Fine"
                }
            }
        ],
        "annotations": []
    }
}
